{
	"id": "org.yakindu.sct.examples.ycar",
	"title": "Webbased YCar App (TypeScript)",
	"author": "itemis AG",
	"description": "This example demonstrates how a state machine can be generated as typescript artifact and how to integrate this into an angular 4 application.",
	"previewImage": "ycar_thumbs.png",
	"category": ["labs",
		"hmi"
	],
	"dependencies": [
		{
			"updateSite": "http://updates.yakindu.com/statecharts/labs",
			"features": ["com.yakindu.sct.generator.typescript.feature.feature.group"]
		}
	]
}
